topsis/102203126.py
topsis/__init__.py
topsis/__main__.py
Topsis_Radhika_102203126-1.0.0.dist-info/LICENSE
Topsis_Radhika_102203126-1.0.0.dist-info/METADATA
Topsis_Radhika_102203126-1.0.0.dist-info/WHEEL
Topsis_Radhika_102203126-1.0.0.dist-info/top_level.txt
Topsis_Radhika_102203126-1.0.0.dist-info/RECORD
