Metadata-Version: 2.2
Name: Topsis-Radhika-102203126
Version: 1.0.0
Summary: A brief description of your package
Home-page: https://github.com/radhikarajdev/topsis_ds.git
Author: Radhika Rajdev
Classifier: Programming Language :: Python :: 3
Classifier: License :: OSI Approved :: MIT License
Classifier: Operating System :: OS Independent
Requires-Python: >=3.6
License-File: LICENSE
Dynamic: author
Dynamic: classifier
Dynamic: description
Dynamic: description-content-type
Dynamic: home-page
Dynamic: requires-python
Dynamic: summary
